{"the":1,"they":20,"there":41,"their":53,"then":60,"them":61,"these":66,"that":10,"than":91,"thank":911,"this":25,"thin":825,"thing":70,"think":133,"third":614,"thick":797,"through":128,"throw":883,"three":153,"though":311,"thought":226,"thousand":480,"those":266,"thus":790,"to":3,"too":148,"took":280,"tool":942,"together":253,"told":343,"top":347,"toward":380,"town":403,"tone":716,"touch":728,"total":943,"time":54,"tire":492,"tiny":682,"tie":833,"two":73,"twenty":695,"take":105,"talk":313,"tall":636,"table":372,"tail":447,"turn":139,"tube":819,"tell":150,"ten":376,"teach":430,"team":732,"test":469,"temperature":640,"term":862,"teeth":998,"try":189,"tree":228,"true":355,"truck":876,"travel":373,"train":558,"trade":700,"track":952,"trip":702,"triangle":826,"trouble":711,"type":629,"of":2,"off":185,"office":703,"offer":973,"often":269,"on":14,"one":23,"only":114,"once":290,"or":27,"order":338,"organ":673,"original":965,"out":37,"our":124,"other":38,"over":88,"old":147,"own":203,"open":251,"operate":800,"opposite":863,"oh":435,"ocean":438,"occur":986,"object":460,"observe":664,"oil":726,"oxygen":901,"a":5,"an":48,"and":4,"any":101,"animal":192,"answer":208,"anger":898,"are":15,"area":335,"arm":513,"art":539,"arrange":868,"arrive":950,"as":17,"ask":179,"at":22,"atom":771,"all":40,"allow":841,"also":157,"always":264,"about":58,"above":307,"able":422,"after":111,"afraid":917,"air":155,"add":168,"act":177,"again":191,"against":383,"ago":481,"age":675,"agree":789,"appear":391,"apple":927,"am":507,"among":500,"i":18,"in":6,"interest":365,"inch":451,"include":527,"instrument":575,"instant":977,"insect":765,"industry":642,"indicate":768,"invent":870,"is":7,"island":465,"it":8,"if":55,"idea":286,"ice":523,"iron":691,"imagine":787,"you":9,"your":45,"young":305,"year":117,"yes":494,"yet":503,"yellow":839,"yard":722,"he":11,"her":67,"here":171,"help":135,"held":616,"head":201,"hear":292,"heard":351,"heart":506,"heat":490,"heavy":509,"his":19,"history":773,"him":72,"high":174,"hill":624,"hit":780,"have":24,"had":28,"has":74,"hand":164,"hard":231,"happen":332,"happy":594,"half":336,"hair":617,"hat":853,"hot":487,"how":46,"home":162,"house":187,"hour":353,"horse":293,"hold":362,"hole":699,"hope":595,"hundred":357,"hunt":543,"human":772,"hurry":828,"huge":918,"was":12,"wash":807,"way":57,"water":90,"watch":296,"want":154,"walk":259,"wall":564,"war":381,"warm":439,"wait":413,"wave":504,"with":16,"will":56,"wild":574,"win":937,"wind":330,"window":555,"winter":571,"wing":804,"wide":514,"wish":567,"wire":733,"wife":864,"word":31,"work":103,"world":195,"would":63,"wood":299,"wonder":478,"won't":792,"woman":752,"women":906,"what":33,"when":42,"where":110,"wheel":456,"whether":610,"which":51,"while":243,"white":255,"who":94,"whole":348,"whose":761,"why":178,"we":35,"were":39,"well":156,"went":182,"west":363,"week":431,"weight":521,"weather":589,"wear":737,"write":62,"written":573,"wrote":714,"wrong":889,"for":13,"form":130,"force":458,"forest":552,"forward":922,"follow":176,"found":207,"four":218,"food":216,"foot":466,"from":26,"front":429,"friend":284,"free":440,"fresh":836,"fraction":551,"fruit":795,"first":93,"fire":339,"find":100,"fine":404,"final":432,"finish":593,"finger":641,"fish":287,"five":358,"fig":916,"figure":415,"fight":644,"field":419,"fill":496,"fit":743,"fat":963,"father":200,"far":236,"farm":230,"face":298,"fact":449,"family":318,"famous":820,"fast":367,"fall":407,"fair":745,"favor":958,"few":249,"feet":275,"feel":312,"feed":941,"felt":530,"fell":742,"fear":823,"fly":406,"flow":744,"flower":596,"floor":620,"flat":694,"full":457,"fun":586,"be":21,"been":98,"before":143,"between":219,"better":354,"begin":257,"began":285,"best":352,"beauty":425,"bear":592,"beat":646,"behind":445,"bed":545,"believe":550,"bell":815,"by":29,"but":32,"build":197,"busy":468,"buy":606,"burn":623,"back":112,"base":291,"basic":944,"ball":502,"baby":601,"bad":724,"bank":746,"band":934,"bat":808,"bar":972,"boy":146,"both":267,"bottom":689,"book":278,"body":316,"box":417,"boat":471,"board":569,"bone":785,"born":872,"bought":928,"big":173,"bird":314,"bit":631,"black":326,"blue":459,"blow":725,"blood":727,"block":851,"brought":489,"brother":546,"broke":654,"brown":736,"broad":893,"bring":493,"bright":587,"break":720,"bread":969,"branch":912,"so":65,"some":34,"sound":83,"south":340,"soon":315,"son":658,"song":322,"soft":585,"solve":608,"soldier":798,"solution":908,"soil":638,"said":47,"sail":515,"say":134,"same":149,"saw":235,"sat":572,"safe":625,"sand":637,"save":748,"salt":895,"she":50,"sheet":956,"shell":999,"show":119,"should":205,"shoulder":866,"shout":712,"short":327,"shore":954,"shoe":865,"shop":881,"ship":334,"shine":884,"shape":485,"shall":615,"sharp":803,"share":966,"see":71,"seem":252,"seed":715,"sent":740,"sentence":131,"sense":650,"send":838,"set":152,"settle":519,"self":198,"sell":854,"select":888,"sea":237,"search":837,"season":907,"seat":949,"second":277,"section":676,"several":378,"seven":612,"serve":390,"separate":755,"segment":974,"side":97,"since":346,"sing":369,"single":692,"six":371,"simple":377,"similar":923,"size":517,"sit":553,"sign":582,"sight":824,"silent":635,"silver":910,"sister":919,"small":159,"smile":697,"smell":945,"spell":167,"special":443,"speak":520,"speed":671,"speech":988,"spend":961,"space":350,"spring":663,"spread":867,"spoke":770,"spot":844,"such":175,"success":855,"sun":217,"sure":295,"surface":462,"surprise":679,"sudden":533,"subject":540,"subtract":857,"substance":957,"summer":557,"suggest":718,"sugar":902,"supply":784,"support":987,"suit":846,"suffix":914,"stand":202,"state":220,"station":967,"star":416,"start":232,"stay":455,"study":211,"student":781,"still":212,"stick":693,"story":234,"store":556,"stop":289,"stood":427,"stone":681,"step":360,"stead":476,"steam":991,"steel":920,"strong":442,"street":450,"stream":822,"stretch":882,"strange":598,"straight":666,"string":814,"school":209,"science":281,"scale":661,"score":926,"slow":385,"sleep":559,"slip":936,"slave":975,"system":467,"syllable":529,"symbol":708,"snow":491,"square":535,"sky":568,"skin":696,"skill":905,"swim":861,"can":36,"call":92,"came":118,"camp":869,"cause":140,"caught":766,"car":274,"care":276,"carry":279,"card":933,"cat":626,"catch":565,"case":655,"captain":753,"capital":791,"could":78,"count":534,"country":206,"course":454,"come":80,"complete":333,"compare":812,"company":856,"common":472,"cover":215,"color":297,"colony":830,"cold":398,"collect":747,"column":886,"correct":421,"corn":811,"corner":782,"contain":428,"control":749,"continue":850,"continent":900,"consider":628,"consonant":667,"condition":940,"connect":959,"cow":579,"cook":619,"cool":684,"coast":632,"coat":931,"copy":633,"cost":734,"cotton":871,"change":181,"chance":879,"character":764,"chart":852,"charge":970,"chair":793,"child":665,"children":256,"chief":829,"chick":981,"check":483,"choose":741,"chord":962,"city":227,"circle":525,"cross":229,"crop":777,"crowd":810,"cry":409,"crease":698,"create":805,"close":245,"clothe":597,"cloud":678,"clock":831,"class":329,"claim":899,"clear":446,"clean":719,"climb":683,"cut":294,"current":847,"cent":730,"center":386,"century":627,"certain":405,"cell":549,"up":43,"us":190,"use":44,"usual":304,"under":125,"until":271,"unit":401,"each":49,"ear":651,"earth":199,"early":361,"ease":261,"east":497,"eat":282,"ever":308,"every":120,"even":169,"event":858,"evening":939,"end":160,"enough":301,"engine":511,"energy":542,"enemy":983,"enter":834,"eye":222,"example":260,"exact":707,"exercise":563,"excite":647,"except":713,"experiment":688,"experience":925,"expect":776,"equate":486,"equal":739,"egg":547,"edge":581,"eight":602,"either":621,"else":652,"electric":775,"element":779,"effect":774,"especially":915,"do":52,"down":96,"does":151,"don't":242,"done":424,"dog":317,"door":324,"doctor":757,"dollar":821,"double":948,"day":77,"dark":410,"dance":510,"danger":794,"dad":968,"did":81,"differ":138,"difficult":756,"direct":319,"distant":495,"discuss":921,"divide":528,"division":955,"dictionary":669,"die":709,"draw":238,"drive":426,"drink":985,"dry":477,"drop":505,"dress":677,"dream":938,"during":356,"duck":976,"develop":437,"decide":461,"decimal":750,"deep":463,"describe":618,"design":685,"desert":845,"depend":816,"dead":843,"deal":860,"death":903,"dear":982,"determine":873,"degree":979,"man":116,"many":59,"make":69,"may":95,"made":108,"mark":268,"market":978,"main":300,"map":393,"machine":411,"material":516,"matter":524,"match":913,"major":835,"magnet":909,"mass":932,"master":951,"more":76,"morning":375,"most":85,"move":144,"mother":194,"motion":992,"mount":566,"mountain":288,"mouth":706,"money":389,"month":590,"moon":464,"moment":660,"modern":778,"molecule":887,"my":87,"me":122,"mean":142,"meant":996,"measure":323,"meat":817,"men":180,"meet":604,"metal":609,"method":672,"melody":701,"much":141,"must":172,"music":265,"multiply":452,"might":233,"mile":272,"million":591,"milk":670,"minute":441,"mind":444,"mine":832,"miss":488,"middle":656,"mix":731,"like":64,"live":109,"little":113,"line":137,"light":183,"life":248,"lift":848,"list":310,"listen":370,"lie":645,"liquid":994,"long":68,"lone":561,"look":75,"low":136,"love":387,"loud":662,"lot":687,"lost":735,"locate":762,"log":995,"large":166,"land":170,"language":499,"last":224,"late":240,"lay":382,"laugh":479,"law":630,"lake":659,"lady":721,"learn":213,"leave":321,"lead":408,"least":710,"let":225,"letter":270,"left":239,"less":374,"length":537,"leg":562,"level":878,"led":929,"go":79,"good":121,"got":258,"govern":396,"gold":473,"gone":599,"get":106,"general":522,"gentle":751,"give":123,"girl":303,"great":132,"green":434,"grew":729,"grow":210,"group":263,"ground":364,"grand":501,"grass":578,"gray":890,"gave":433,"game":484,"gas":588,"garden":738,"gather":880,"glass":577,"glad":964,"guess":801,"gun":840,"guide":924,"number":82,"numeral":328,"no":84,"now":99,"nor":947,"north":250,"notice":399,"note":412,"nothing":453,"noun":418,"noon":760,"noise":877,"nose":896,"new":102,"need":186,"near":196,"never":223,"next":254,"necessary":802,"neck":1000,"neighbor":806,"name":126,"natural":648,"nature":989,"nation":668,"night":246,"nine":875,"people":86,"person":388,"perhaps":531,"period":767,"part":104,"party":783,"particular":859,"paragraph":613,"parent":953,"page":204,"paper":262,"pass":345,"past":584,"pattern":384,"path":993,"paint":498,"pair":526,"pay":674,"place":107,"play":158,"plan":414,"plant":214,"plane":475,"planet":827,"plain":302,"please":758,"plural":897,"put":161,"pull":397,"push":611,"port":165,"point":193,"pose":320,"possible":474,"position":512,"post":960,"power":402,"pound":423,"poor":686,"poem":813,"populate":980,"picture":188,"pick":532,"piece":342,"pitch":930,"press":244,"present":508,"prepare":894,"pretty":904,"product":325,"produce":448,"problem":341,"probable":544,"prove":560,"provide":788,"protect":759,"process":799,"proper":971,"property":885,"practice":754,"print":842,"phrase":634,"know":89,"knew":344,"kind":184,"king":349,"kill":657,"keep":221,"kept":576,"key":690,"round":115,"room":283,"root":605,"rock":337,"road":392,"roll":639,"row":705,"rose":849,"rope":935,"right":145,"river":273,"ride":548,"rise":723,"ring":763,"rich":796,"read":163,"ready":306,"real":247,"reach":366,"reason":536,"red":309,"remember":359,"rest":420,"result":622,"record":470,"receive":704,"represent":538,"repeat":891,"reply":984,"region":541,"require":892,"run":241,"rule":395,"rub":818,"rain":394,"raise":607,"rail":786,"ran":482,"range":990,"race":554,"radio":769,"rather":809,"very":127,"verb":368,"vowel":379,"voice":400,"vary":518,"value":643,"valley":946,"visit":583,"village":603,"view":649,"just":129,"jump":600,"joy":570,"job":580,"join":717,"question":331,"quick":436,"quite":653,"quiet":680,"quart":874,"quotient":997}